scaledown/__init__.py
scaledown/loader.py
scaledown/converter/__init__.py
scaledown/converter/convert_to_onnx.py
scaledown/converter/convert_to_tf.py
scaledown/distillation/__init__.py
scaledown/distillation/knowledge_distillation.py
scaledown/models/__init__.py
scaledown/models/tensorflow_model.py
scaledown/quantization/__init__.py
scaledown/quantization/activation_quantization.py
scaledown/quantization/quantization.py
scaledown/quantization/weight_quantization.py
sd_nightly-0.0.5.dev20221108.dist-info/LICENSE
sd_nightly-0.0.5.dev20221108.dist-info/METADATA
sd_nightly-0.0.5.dev20221108.dist-info/WHEEL
sd_nightly-0.0.5.dev20221108.dist-info/top_level.txt
sd_nightly-0.0.5.dev20221108.dist-info/RECORD
