Metadata-Version: 2.1
Name: sd-nightly
Version: 0.0.5.dev20221108
Summary: Scaledown is an Open Source Neural Network Optimization Framework for TinyML Devices
Home-page: https://github.com/scaledown-team/scaledown
Author: csoham
Author-email: hello@csoham.com
Project-URL: Bug Tracker, https://github.com/scaledown-team/scaledown/issues
Classifier: Programming Language :: Python :: 3
Classifier: License :: OSI Approved :: GNU General Public License v3 (GPLv3)
Classifier: Operating System :: OS Independent
Requires-Python: >=3.6
License-File: LICENSE
